odoo/addons/user_log_view/README.rst
odoo/addons/user_log_view/__init__.py
odoo/addons/user_log_view/__manifest__.py
odoo/addons/user_log_view/i18n/it.po
odoo/addons/user_log_view/i18n/user_log_view.pot
odoo/addons/user_log_view/readme/CONTRIBUTORS.md
odoo/addons/user_log_view/readme/DESCRIPTION.md
odoo/addons/user_log_view/readme/USAGE.md
odoo/addons/user_log_view/static/description/icon.png
odoo/addons/user_log_view/static/description/index.html
odoo/addons/user_log_view/views/res_users_views.xml
odoo_addon_user_log_view-18.0.1.0.0.2.dist-info/METADATA
odoo_addon_user_log_view-18.0.1.0.0.2.dist-info/WHEEL
odoo_addon_user_log_view-18.0.1.0.0.2.dist-info/top_level.txt
odoo_addon_user_log_view-18.0.1.0.0.2.dist-info/RECORD
